b64url.py
b64url.pyi
b64url-0.1.3.dist-info/LICENSE
b64url-0.1.3.dist-info/METADATA
b64url-0.1.3.dist-info/WHEEL
b64url-0.1.3.dist-info/RECORD
