Metadata-Version: 2.1
Name: b64url
Version: 0.1.3
Summary: Utilities for handling Data URLs
License: MIT
Author: Abi Raja
Author-email: abimanyuraja@gmail.com
Requires-Python: >=3.10,<4.0
Classifier: License :: OSI Approved :: MIT License
Classifier: Programming Language :: Python :: 3
Classifier: Programming Language :: Python :: 3.10
Classifier: Programming Language :: Python :: 3.11
Classifier: Programming Language :: Python :: 3.12
